Workbook

Sheet Динамика
A1: Недельная динамика спроса и лидов
A2: Лиды и качественные лиды — левая шкала; запросы Wordstat — правая шкала
A35: Шаг данных — 1 неделя. Подписи на оси показаны реже для читаемости; каждая точка линии соответствует отдельной неделе.

Sheet Дашборд
A1: Левша — спрос на плёнку и лиды
A2: Недельная аналитика: 27.12.2021–12.07.2026
A4: Всего лидов | D4: Качественных лидов | G4: Запросов Wordstat | J4: Недель в анализе
A5: =SUM('Недельная сводка'!D5:D241) -> 4733 | D5: =SUM('Недельная сводка'!E5:E241) -> 4592 | G5: =SUM('Недельная сводка'!F5:F241) -> 11212 | J5: 237
A8: Корреляция Пирсона
A9: Показатель | B9: Коэффициент r | C9: Интерпретация
A10: Запросы ↔ все лиды | B10: =CORREL('Недельная сводка'!F5:F241,'Недельная сводка'!D5:D241) -> 0.45366233 | C10: =IF(ABS(B10)<0.3,"Слабая",IF(ABS(B10)<0.7,"Умеренная","Сильная")) -> Умеренная
A11: Запросы ↔ качественные лиды | B11: =CORREL('Недельная сводка'!F5:F241,'Недельная сводка'!E5:E241) -> 0.45919228 | C11: =IF(ABS(B11)<0.3,"Слабая",IF(ABS(B11)<0.7,"Умеренная","Сильная")) -> Умеренная
A13: Примечание: последняя неделя лидов 13–19.07.2026 исключена, так как соответствующего периода нет в выгрузке Wordstat.

Sheet Недельная сводка
A1: Левша — плёнка: лиды и спрос Wordstat по неделям
A2: Периоды заданы выгрузкой Wordstat. Успешный лид = стадия «Качественный лид».
A4: Начало недели | B4: Конец недели | C4: Период Wordstat | D4: Все лиды | E4: Качественные лиды | F4: Запросы Wordstat | G4: Доля качественных
A5: 44557 | B5: 44563 | C5: 27 декабря 2021 – 2 января 2022 | D5: =COUNTIFS('Исходник — лиды'!$H$2:$H$4774,">="&A5,'Исходник — лиды'!$H$2:$H$4774,"<"&B5+1) -> 1 | E5: =COUNTIFS('Исходник — лиды'!$H$2:$H$4774,">="&A5,'Исходник — лиды'!$H$2:$H$4774,"<"&B5+1,'Исходник — лиды'!$C$2:$C$4774,"Качественный лид") -> 0 | F5: 23 | G5: =IFERROR(E5/D5,0) -> 0
A6: 44564 | B6: 44570 | C6: 3 января 2022 – 9 января 2022 | D6: =COUNTIFS('Исходник — лиды'!$H$2:$H$4774,">="&A6,'Исходник — лиды'!$H$2:$H$4774,"<"&B6+1) -> 16 | E6: =COUNTIFS('Исходник — лиды'!$H$2:$H$4774,">="&A6,'Исходник — лиды'!$H$2:$H$4774,"<"&B6+1,'Исходник — лиды'!$C$2:$C$4774,"Качественный лид") -> 12 | F6: 31 | G6: =IFERROR(E6/D6,0) -> 0.75
A7: 44571 | B7: 44577 | C7: 10 января 2022 – 16 января 2022 | D7: =COUNTIFS('Исходник — лиды'!$H$2:$H$4774,">="&A7,'Исходник — лиды'!$H$2:$H$4774,"<"&B7+1) -> 20 | E7: =COUNTIFS('Исходник — лиды'!$H$2:$H$4774,">="&A7,'Исходник — лиды'!$H$2:$H$4774,"<"&B7+1,'Исходник — лиды'!$C$2:$C$4774,"Качественный лид") -> 19 | F7: 17 | G7: =IFERROR(E7/D7,0) -> 0.95
A8: 44578 | B8: 44584 | C8: 17 января 2022 – 23 января 2022 | D8: =COUNTIFS('Исходник — лиды'!$H$2:$H$4774,">="&A8,'Исходник — лиды'!$H$2:$H$4774,"<"&B8+1) -> 23 | E8: =COUNTIFS('Исходник — лиды'!$H$2:$H$4774,">="&A8,'Исходник — лиды'!$H$2:$H$4774,"<"&B8+1,'Исходник — лиды'!$C$2:$C$4774,"Качественный лид") -> 21 | F8: 25 | G8: =IFERROR(E8/D8,0) -> 0.91304348
A9: 44585 | B9: 44591 | C9: 24 января 2022 – 30 января 2022 | D9: =COUNTIFS('Исходник — лиды'!$H$2:$H$4774,">="&A9,'Исходник — лиды'!$H$2:$H$4774,"<"&B9+1) -> 19 | E9: =COUNTIFS('Исходник — лиды'!$H$2:$H$4774,">="&A9,'Исходник — лиды'!$H$2:$H$4774,"<"&B9+1,'Исходник — лиды'!$C$2:$C$4774,"Качественный лид") -> 18 | F9: 34 | G9: =IFERROR(E9/D9,0) -> 0.94736842
A10: 44592 | B10: 44598 | C10: 31 января 2022 – 6 февраля 2022 | D10: =COUNTIFS('Исходник — лиды'!$H$2:$H$4774,">="&A10,'Исходник — лиды'!$H$2:$H$4774,"<"&B10+1) -> 13 | E10: =COUNTIFS('Исходник — лиды'!$H$2:$H$4774,">="&A10,'Исходник — лиды'!$H$2:$H$4774,"<"&B10+1,'Исходник — лиды'!$C$2:$C$4774,"Качественный лид") -> 13 | F10: 35 | G10: =IFERROR(E10/D10,0) -> 1
A11: 44599 | B11: 44605 | C11: 7 февраля 2022 – 13 февраля 2022 | D11: =COUNTIFS('Исходник — лиды'!$H$2:$H$4774,">="&A11,'Исходник — лиды'!$H$2:$H$4774,"<"&B11+1) -> 17 | E11: =COUNTIFS('Исходник — лиды'!$H$2:$H$4774,">="&A11,'Исходник — лиды'!$H$2:$H$4774,"<"&B11+1,'Исходник — лиды'!$C$2:$C$4774,"Качественный лид") -> 17 | F11: 60 | G11: =IFERROR(E11/D11,0) -> 1
A12: 44606 | B12: 44612 | C12: 14 февраля 2022 – 20 февраля 2022 | D12: =COUNTIFS('Исходник — лиды'!$H$2:$H$4774,">="&A12,'Исходник — лиды'!$H$2:$H$4774,"<"&B12+1) -> 18 | E12: =COUNTIFS('Исходник — лиды'!$H$2:$H$4774,">="&A12,'Исходник — лиды'!$H$2:$H$4774,"<"&B12+1,'Исходник — лиды'!$C$2:$C$4774,"Качественный лид") -> 17 | F12: 43 | G12: =IFERROR(E12/D12,0) -> 0.94444444
A13: 44613 | B13: 44619 | C13: 21 февраля 2022 – 27 февраля 2022 | D13: =COUNTIFS('Исходник — лиды'!$H$2:$H$4774,">="&A13,'Исходник — лиды'!$H$2:$H$4774,"<"&B13+1) -> 15 | E13: =COUNTIFS('Исходник — лиды'!$H$2:$H$4774,">="&A13,'Исходник — лиды'!$H$2:$H$4774,"<"&B13+1,'Исходник — лиды'!$C$2:$C$4774,"Качественный лид") -> 12 | F13: 27 | G13: =IFERROR(E13/D13,0) -> 0.8
A14: 44620 | B14: 44626 | C14: 28 февраля 2022 – 6 марта 2022 | D14: =COUNTIFS('Исходник — лиды'!$H$2:$H$4774,">="&A14,'Исходник — лиды'!$H$2:$H$4774,"<"&B14+1) -> 14 | E14: =COUNTIFS('Исходник — лиды'!$H$2:$H$4774,">="&A14,'Исходник — лиды'!$H$2:$H$4774,"<"&B14+1,'Исходник — лиды'!$C$2:$C$4774,"Качественный лид") -> 14 | F14: 32 | G14: =IFERROR(E14/D14,0) -> 1
A15: 44627 | B15: 44633 | C15: 7 марта 2022 – 13 марта 2022 | D15: =COUNTIFS('Исходник — лиды'!$H$2:$H$4774,">="&A15,'Исходник — лиды'!$H$2:$H$4774,"<"&B15+1) -> 22 | E15: =COUNTIFS('Исходник — лиды'!$H$2:$H$4774,">="&A15,'Исходник — лиды'!$H$2:$H$4774,"<"&B15+1,'Исходник — лиды'!$C$2:$C$4774,"Качественный лид") -> 20 | F15: 23 | G15: =IFERROR(E15/D15,0) -> 0.90909091
A16: 44634 | B16: 44640 | C16: 14 марта 2022 – 20 марта 2022 | D16: =COUNTIFS('Исходник — лиды'!$H$2:$H$4774,">="&A16,'Исходник — лиды'!$H$2:$H$4774,"<"&B16+1) -> 11 | E16: =COUNTIFS('Исходник — лиды'!$H$2:$H$4774,">="&A16,'Исходник — лиды'!$H$2:$H$4774,"<"&B16+1,'Исходник — лиды'!$C$2:$C$4774,"Качественный лид") -> 11 | F16: 31 | G16: =IFERROR(E16/D16,0) -> 1
... A241: 46209 | B241: 46215 | C241: 6 июля 2026 – 12 июля 2026 | D241: =COUNTIFS('Исходник — лиды'!$H$2:$H$4774,">="&A241,'Исходник — лиды'!$H$2:$H$4774,"<"&B241+1) -> 30 | E241: =COUNTIFS('Исходник — лиды'!$H$2:$H$4774,">="&A241,'Исходник — лиды'!$H$2:$H$4774,"<"&B241+1,'Исходник — лиды'!$C$2:$C$4774,"Качественный лид") -> 27 | F241: 85 | G241: =IFERROR(E241/D241,0) -> 0.9

Sheet Исходник — лиды
A1: Название лида | B1: Источник | C1: Стадия | D1: Обращение | E1: Имя | F1: Отчество | G1: Фамилия | H1: Дата создания | I1: Ответственный | J1: Путь клиента | K1: UTM Source | L1: UTM Medium | M1: UTM Campaign | N1: UTM Content | O1: UTM Term | P1: ДКТ: client_id | Q1: ДКТ: client_cid | R1: ДКТ: ya_client_id | S1: ДКТ: Город | T1: ДКТ: Источник | U1: ДКТ: Канал | V1: ДКТ: Кампания | W1: ДКТ: Содержимое | X1: ДКТ: Что искал | Y1: ДКТ: Время на сайте | Z1: ID
A2: консультация по пленке | B2: Звонок | C2: Качественный лид | H2: 46222.864 | I2: Богдан Клименко | Z2: 114236
A3: лада веста чёрная | B3: Звонок | C3: Качественный лид | H3: 46222.602 | I3: Александр Шушкин | Z3: 114227
A4: притемнить фары | B4: Звонок | C4: Качественный лид | H4: 46222.424 | I4: Александр Шушкин | Z4: 114223
A5: плёнка | B5: Звонок | C5: Качественный лид | H5: 46221.782 | I5: Александр Шушкин | K5: yandex | L5: cpc | M5: 708209804 | N5: 17657889986 | O5: Обтяжка автомобиля пленкой.mobile.Елшанское сельское поселение | P5: 5OCLwgMZHeY38wXEctOA | R5: 1.7843858e+18 | S5: Самара | T5: yandex | U5: cpc | V5: 708209804 | W5: 17657889986 | X5: Обтяжка автомобиля пленкой.mobile.Елшанское сельское поселение | Y5: 78 | Z5: 114216
A6: пленка и тонировка атермалка | B6: Звонок | C6: Качественный лид | H6: 46221.711 | I6: Александр Шушкин | K6: google | L6: organic | M6: (none) | N6: (none) | O6: (none) | P6: 1SKG5fQDcPkdOTh682F0 | R6: 1.7843031e+17 | S6: Самара | T6: google | U6: organic | V6: (none) | W6: (none) | X6: (none) | Y6: 281 | Z6: 114212
A7: плёнка | B7: Звонок | C7: Качественный лид | H7: 46221.666 | I7: Александр Шушкин | K7: google | L7: organic | M7: (none) | N7: (none) | O7: (none) | P7: Ox2cqqcN9g7kBRM3bEYK | R7: 1.7843759e+18 | S7: Самара | T7: google | U7: organic | V7: (none) | W7: (none) | X7: (none) | Y7: 3 | Z7: 114211
A8: фары на Фере оклеить | B8: Веб-сайт | C8: Качественный лид | E8: тимур | H8: 46221.495 | I8: Александр Шушкин | K8: levsha-group.ru | Z8: 114204
A9: плёнка | B9: Звонок | C9: Качественный лид | H9: 46221.482 | I9: Александр Шушкин | K9: yandex | L9: organic | M9: (none) | N9: / | O9: (none) | P9: b9TUL2DuFwRzjOEx8DUP | R9: 1.78436e+18 | S9: Воронеж | T9: yandex | U9: organic | V9: (none) | W9: / | X9: (none) | Y9: 25 | Z9: 114202
A10: Зона рисков нива тревел | B10: Звонок | C10: В работе | H10: 46220.563 | I10: Алексей Торгашëв | Z10: 114175
A11: Пленка стандарт с бампером Лисян | B11: Звонок | C11: Качественный лид | H11: 46220.496 | I11: Виктор Худяков | Z11: 114172
A12: закатать крышу чёрной плёнкой / молчит | B12: Avito - Левша-Сервис открытая линия | C12: Качественный лид | E12: Игорь | H12: 46220.372 | I12: Алексей Торгашëв | Z12: 114164
A13: Сергей - Авито - Левша-Сервис открытая линия / веду диалог на авито | B13: Avito - Левша-Сервис открытая линия | C13: В работе | E13: Сергей | H13: 46219.894 | I13: Алексей Торгашëв | Z13: 114160
A14: БМВ 3 ф30 в цветную нарды-грей / узнавал цены | B14: Звонок | C14: В работе | H14: 46219.71 | I14: Алексей Торгашëв | Z14: 114154
A15: Оклейка капота соболя с принтом | B15: Звонок | C15: Качественный лид | H15: 46219.522 | I15: Виктор Худяков | K15: yandex | L15: cpc | M15: 708209804 | N15: 17657889986 | O15: Обтяжка автомобиля пленкой.mobile.Орск | P15: mlwar5b9UMGJBmnIn83w | R15: 1.7841906e+18 | S15: Сочи | T15: yandex | U15: cpc | V15: 708209804 | W15: 17657889986 | X15: Обтяжка автомобиля пленкой.mobile.Орск | Y15: 4 | Z15: 114137
A16: Джили ситирей зоны риска | B16: Звонок | C16: В работе | H16: 46219.443 | I16: Алексей Торгашëв | Z16: 114129
A17: оклейки крыши лада Гранта | B17: Avito - Левша-Сервис открытая линия | C17: Качественный лид | E17: FOG | G17: AUTO | H17: 46219.409 | I17: Виктор Худяков | Z17: 114125
A18: Оклеить крышу оптима в черный глянец / чат | B18: Avito - Левша-Сервис открытая линия | C18: В работе | E18: Александр | H18: 46219.368 | I18: Алексей Торгашëв | Z18: 114121
A19: Яна Баринова - Открытая линия Левша | B19: ВКонтакте - Открытая линия Левша | C19: Клиенту ответили на вопрос | E19: Яна | G19: Баринова | H19: 46218.801 | I19: Богдан Клименко | Z19: 114114
A20: темный полик тигуан на фонари узновал цену | B20: Звонок | C20: Клиенту ответили на вопрос | H20: 46218.713 | I20: Богдан Клименко | Z20: 114106
A21: узновал по пленке на капот | B21: Звонок | C21: Клиенту ответили на вопрос | H21: 46218.704 | I21: Лида Левша | K21: yandex | L21: cpc | M21: 708209804 | N21: 17657889986 | O21: Сколько стоит оклеить авто.mobile.Алексеевка | P21: QCa5hOt6NuhefCl8y0u9 | R21: 1.78412e+18 | S21: Москва | T21: yandex | U21: cpc | V21: 708209804 | W21: 17657889986 | X21: Сколько стоит оклеить авто.mobile.Алексеевка | Y21: 6 | Z21: 114105
A22: оклейка пленкой ауди а 6 дорого | B22: Face-трекер | C22: Качественный лид | H22: 46218.542 | I22: Лида Левша | Z22: 114091
A23: Оклейка 20 автобусов | B23: Звонок | C23: Качественный лид | H23: 46218.529 | I23: Виктор Худяков | K23: yandex | L23: cpc | M23: 708209804 | N23: 17710448884 | O23: ---autotargeting.desktop.Самара | P23: dUk7zioJc4mnx9p4BsOG | R23: 1.7841048e+18 | S23: Самара | T23: yandex | U23: cpc | V23: 708209804 | W23: 17710448884 | X23: ---autotargeting.desktop.Самара | Y23: 4 | Z23: 114089
A24: узновал цену на лисян л9 комплекс брони | B24: Звонок | C24: Качественный лид | H24: 46218.449 | I24: Богдан Клименко | Z24: 114081
A25: оклейка лада весты кросс | B25: Звонок | C25: Качественный лид | H25: 46218.425 | I25: Богдан Клименко | K25: google | L25: organic | M25: (none) | N25: (none) | O25: (none) | P25: PW4YQgd6q9YZpWI0rYco | R25: 1.7840959e+18 | S25: Москва | T25: google | U25: organic | V25: (none) | W25: (none) | X25: (none) | Y25: 15 | Z25: 114077
A26: Александр - Авито - Левша-Сервис открытая линия | B26: Avito - Левша-Сервис открытая линия | C26: Клиенту ответили на вопрос | E26: Александр | H26: 46217.833 | I26: Богдан Клименко | Z26: 114067
A27: узновала цену на пленку | B27: ВКонтакте - Открытая линия Левша | C27: Клиенту ответили на вопрос | E27: Яна | G27: Баринова | H27: 46217.743 | I27: Лида Левша | Z27: 114063
A28: каптюр оклейка фар подумает | B28: Звонок | C28: Качественный лид | H28: 46217.645 | I28: Богдан Клименко | Z28: 114053
A29: bmw 1 2006 г в цветную пленку 300к дорого | B29: Звонок | C29: Качественный лид | H29: 46217.642 | I29: Богдан Клименко | Z29: 114052
A30: плёнка панорама на 15,07 | B30: Звонок | C30: Качественный лид | H30: 46217.562 | I30: Александр Шушкин | K30: google | L30: organic | M30: (none) | N30: (none) | O30: (none) | P30: 6wTGAHs8ApvGk0zlI6Gp | R30: 1.7803125e+18 | S30: Самара | T30: google | U30: organic | V30: (none) | W30: (none) | X30: (none) | Y30: 3 | Z30: 114044
A31: сергей - Авито - Левша-Сервис открытая линия | B31: Avito - Левша-Сервис открытая линия | C31: Клиенту ответили на вопрос | E31: сергей | H31: 46217.554 | I31: Богдан Клименко | Z31: 114042
A32: Дмитрий - Авито - Левша-Сервис открытая линия | B32: Avito - Левша-Сервис открытая линия | C32: Клиенту ответили на вопрос | E32: Дмитрий | H32: 46217.542 | I32: Богдан Клименко | Z32: 114041
A33: плёнка на пороги в чёрн. глян. | B33: Avito - Левша-Сервис открытая линия | C33: Качественный лид | E33: Валентин | H33: 46217.519 | I33: Александр Шушкин | Z33: 114040
A34: фары оклеить в следующем месяце | B34: Звонок | C34: Качественный лид | H34: 46217.514 | I34: Александр Шушкин | Z34: 114038
A35: гранта оклейка пленкой - верх багажника и бампер зад 30000 рокет ДОРОГО | B35: Звонок | C35: Качественный лид | H35: 46217.504 | I35: Богдан Клименко | K35: yandex | L35: organic | M35: (none) | N35: / | O35: (none) | P35: ZAy7XBLnqACQ0L5EUX5V | R35: 1.7840156e+18 | S35: Самара | T35: yandex | U35: organic | V35: (none) | W35: / | X35: (none) | Y35: 60 | Z35: 114036
A36: Кайрат - Авито - Левша-Сервис открытая линия | B36: Avito - Левша-Сервис открытая линия | C36: Клиенту ответили на вопрос | E36: Кайрат | H36: 46217.376 | I36: Богдан Клименко | Z36: 114022
A37: Мария - Авито - Левша-Сервис открытая линия | B37: Avito - Левша-Сервис открытая линия | C37: Клиенту ответили на вопрос | E37: Мария | H37: 46217.374 | I37: Богдан Клименко | Z37: 114021
A38: полная оклейка мустанг дорого | B38: Звонок | C38: Качественный лид | H38: 46216.749 | I38: Богдан Клименко | Z38: 114014
A39: kia K5 оклеить целиком | B39: Звонок | C39: Качественный лид | H39: 46216.656 | I39: Александр Шушкин | Z39: 114008
A40: плёнка бампер | B40: Звонок | C40: Качественный лид | H40: 46216.46 | I40: Александр Шушкин | K40: yandex | L40: organic | M40: (none) | N40: / | O40: (none) | P40: dqrGaxLpxOVGsUXa3lur | S40: Самара | T40: yandex | U40: organic | V40: (none) | W40: / | X40: (none) | Y40: 0 | Z40: 113991
A41: пленка решетки спортаж 5 | B41: Звонок | C41: Качественный лид | H41: 46216.37 | I41: Богдан Клименко | K41: google | L41: organic | M41: (none) | N41: (none) | O41: (none) | P41: ckgXLzwfRpzpNBOqBjJN | R41: 1.7820276e+18 | S41: Самара | T41: google | U41: organic | V41: (none) | W41: (none) | X41: (none) | Y41: 3 | Z41: 113984
A42: Стандарт с бампером и тонировка в круг | B42: Веб-сайт | C42: Качественный лид | E42: Игорб | H42: 46214.433 | I42: Виктор Худяков | K42: levsha-group.ru | Z42: 113970
A43: Дмитрий - Авито - Оклейка стандарт Рокетом | B43: Avito - Левша-Сервис открытая линия | C43: Качественный лид | E43: Дмитрий | H43: 46214.383 | I43: Виктор Худяков | Z43: 113965
A44: Октавия крыша в черный глянец | B44: Звонок | C44: В работе | H44: 46213.807 | I44: Алексей Торгашëв | Z44: 113959
A45: 14,07 Осмотр пленки | B45: Звонок | C45: Качественный лид | H45: 46213.688 | I45: Виктор Худяков | Z45: 113946
A46: Оклейка трактора | B46: Звонок | C46: Качественный лид | H46: 46213.598 | I46: Виктор Худяков | K46: yandex | L46: organic | M46: (none) | N46: / | O46: (none) | P46: XPbM64pNd1ppV4NATdan | R46: 1.7660522e+18 | S46: Ульяновск | T46: yandex | U46: organic | V46: (none) | W46: / | X46: (none) | Y46: 1657 | Z46: 113935
A47: чайна таун тенет т7 , мойка шви и пленка 2 машины ждут расчет на почту | B47: Звонок | C47: Качественный лид | H47: 46212.744 | I47: Богдан Клименко | Z47: 113920
A48: Хонда Тайп р полная оклейка | B48: Звонок | C48: Качественный лид | H48: 46212.732 | I48: Виктор Худяков | K48: google | L48: organic | M48: (none) | N48: (none) | O48: (none) | P48: Q96QNGQV5HOsqiUdIg2D | R48: 1.7836041e+18 | S48: Уфа | T48: google | U48: organic | V48: (none) | W48: (none) | X48: (none) | Y48: 3 | Z48: 113919
A49: хайлендр пленка комплекс броня | B49: Звонок | C49: Качественный лид | H49: 46212.469 | I49: Богдан Клименко | K49: yandex | L49: cpc | M49: 708209804 | N49: 17710448884 | O49: Бронирование кузова.mobile.Кошки | P49: YP9q8oHpLQajZaolJ2zN | R49: 1.7835812e+18 | S49: Самара | T49: yandex | U49: cpc | V49: 708209804 | W49: 17710448884 | X49: Бронирование кузова.mobile.Кошки | Y49: 82 | Z49: 113902
A50: ВсЁ пО чЕсТнОмУ - Авито - Левша-Сервис открытая линия | B50: Avito - Левша-Сервис открытая линия | C50: Качественный лид | E50: ВсЁ пО чЕсТнОмУ | H50: 46211.992 | I50: Богдан Клименко | Z50: 113895
A51: пленка аутлендер | B51: Avito - Левша-Сервис открытая линия | C51: Качественный лид | E51: Пользователь | H51: 46211.791 | I51: Богдан Клименко | Z51: 113891
A52: пленка Geely EX5 EM-i комплекс дорого | C52: Качественный лид | E52: Игорь | H52: 46211.695 | I52: Лида Левша | K52: tilda | L52: cpc | M52: 708209804 | N52: 17710448884 | O52: ---autotargeting.desktop.Самара | Z52: 113882
A53: консультация по пленке audi q 3 | B53: Звонок | C53: Качественный лид | H53: 46211.569 | I53: Богдан Клименко | K53: yandex | L53: cpc | M53: 708209804 | N53: 17710448884 | O53: Оклейка зон риска.mobile.Самара | P53: 1XR2qcrpBM45PuAK0Eim | R53: 1.7835036e+18 | S53: Новочебоксарск | T53: yandex | U53: cpc | V53: 708209804 | W53: 17710448884 | X53: Оклейка зон риска.mobile.Самара | Y53: 34 | Z53: 113878
A54: пленка консультация | C54: Качественный лид | E54: Кирилл | H54: 46210.962 | I54: Богдан Клименко | K54: tilda | L54: cpc | M54: 708209804 | N54: 17657889986 | O54: Оклейка авто.mobile.Самара | Z54: 113867
A55: оклейка фар консультация | C55: Качественный лид | E55: Владимир | H55: 46210.937 | I55: Богдан Клименко | K55: tilda | L55: cpc | M55: 708209804 | N55: 17657889986 | O55: Оклейка автомобиля.mobile.Сельское поселение Лопатино | Z55: 113866
A56: гольф , броне комплекс пленка , тонер пп , химка комплекс позвонить посоветуются | C56: Качественный лид | E56: илья | H56: 46210.812 | I56: Богдан Клименко | K56: tilda | L56: cpc | M56: 708209804 | N56: 17710448884 | O56: ---autotargeting.desktop.Самара | Z56: 113861
A57: плёнка | B57: Звонок | C57: Качественный лид | H57: 46210.793 | I57: Александр Шушкин | Z57: 113860
A58: плёнка на капот | B58: Звонок | C58: Качественный лид | H58: 46210.651 | I58: Александр Шушкин | Z58: 113846
A59: оклейка пленкой бронек комплекс плюс лоб броня | B59: Звонок | C59: Качественный лид | H59: 46210.514 | I59: Богдан Клименко | Z59: 113835
A60: плёнка | B60: Звонок | C60: Качественный лид | H60: 46210.48 | I60: Александр Шушкин | K60: google | L60: organic | M60: (none) | N60: (none) | O60: (none) | P60: eRQ3DnlSzveMfkBgkkPQ | S60: Бузулук | T60: google | U60: organic | V60: (none) | W60: (none) | X60: (none) | Y60: 0 | Z60: 113830
A61: не берет чат плёнка | C61: Клиент не выходит на связь | E61: Иван | H61: 46209.697 | I61: Александр Шушкин | K61: tilda | L61: cpc | M61: 708209804 | N61: 17710448884 | O61: ---autotargeting.mobile.Самара | Z61: 113811
A62: полировка фар | B62: Звонок | C62: Качественный лид | H62: 46209.696 | I62: Александр Шушкин | K62: yandex | L62: cpc | M62: 708209804 | N62: 17710448884 | O62: Оклейка фар.desktop.Самара | P62: 5oUYmXvkTrm2sFbSneUw | R62: 1.7833417e+18 | S62: Самара | T62: yandex | U62: cpc | V62: 708209804 | W62: 17710448884 | X62: Оклейка фар.desktop.Самара | Y62: 6 | Z62: 113810
A63: Плёнк. чёрн. крыша | B63: Звонок | C63: Качественный лид | H63: 46209.654 | I63: Александр Шушкин | Z63: 113802
A64: ауди а4 оклейка в полированный хром | B64: Звонок | C64: В работе | H64: 46209.598 | I64: Алексей Торгашëв | Z64: 113799
A65: демонтаж плёнки с капота на 13,07 | B65: Звонок | C65: Качественный лид | H65: 46209.578 | I65: Александр Шушкин | K65: google | L65: organic | M65: (none) | N65: (none) | O65: (none) | P65: O3k5WMQKzKom2oCESMrP | R65: 1.7833316e+18 | S65: Краснодар | T65: google | U65: organic | V65: (none) | W65: (none) | X65: (none) | Y65: 3 | Z65: 113796
A66: плёнка | C66: Качественный лид | E66: татьяна | H66: 46209.572 | I66: Александр Шушкин | K66: tilda | L66: cpc | M66: 708209804 | N66: 17657889986 | O66: Нанести пленку на автомобиль.desktop.Самара | Z66: 113793
A67: плёнка на капот | B67: Avito - Левша-Сервис открытая линия | C67: Качественный лид | E67: Надя | G67: Кочемазова | H67: 46209.548 | I67: Александр Шушкин | Z67: 113791
A68: плёнка гранта по чат | C68: Качественный лид | E68: Юрий Петрович | H68: 46209.548 | I68: Александр Шушкин | K68: tilda | L68: cpc | M68: 708209804 | N68: 17710448884 | O68: ---autotargeting.tablet.Самара | Z68: 113790
A69: плёнка на 07,07 | B69: Веб-сайт | C69: Качественный лид | E69: Дмитрий | H69: 46209.54 | I69: Александр Шушкин | K69: levsha-group.ru | Z69: 113787
A70: плёнка на фары вояж | B70: Звонок | C70: Качественный лид | H70: 46209.475 | I70: Александр Шушкин | Z70: 113779
A71: оклеить капот на старую пленку для рыбалки | C71: Качественный лид | E71: Александр | H71: 46209.445 | I71: Лида Левша | K71: tilda | L71: cpc | M71: 708209804 | N71: 17710448884 | O71: ---autotargeting.mobile.Самара | Z71: 113777
A72: Х6 ф19 в сатин / узнает цены / мы первые кого выдал поиск | B72: Звонок | C72: Качественный лид | H72: 46208.888 | I72: Алексей Торгашëв | Z72: 113771
A73: КРыша черный глянец Веста | B73: Звонок | C73: Качественный лид | H73: 46208.703 | I73: Виктор Худяков | K73: ya_maps | L73: (none) | M73: (none) | N73: (none) | O73: (none) | P73: silwKVsfXEeE8cta8u70 | R73: 1.7832559e+18 | S73: Самара | T73: ya_maps | U73: (none) | V73: (none) | W73: (none) | X73: (none) | Y73: 4 | Z73: 113766
A74: Мазда сх-50 зоны риска с бампером / машина в пути до конца июля | B74: Звонок | C74: Качественный лид | H74: 46208.702 | I74: Алексей Торгашëв | K74: yandex | L74: cpc | M74: 119789135 | N74: 16990012918 | O74: ---autotargeting.mobile.Самара | P74: 7hKX64kqfZK3VOaXWY5i | R74: 1.7832558e+18 | S74: Самара | T74: yandex | U74: cpc | V74: 119789135 | W74: 16990012918 | X74: ---autotargeting.mobile.Самара | Y74: 7 | Z74: 113764
A75: Полная оклейка ваз 21099 | C75: Качественный лид | E75: Константин | H75: 46207.977 | I75: Виктор Худяков | K75: tilda | Z75: 113748
A76: Лид #113747 / пообщались / это дубликат / сделка есть | C76: Дубликат | E76: Юрий | H76: 46207.872 | I76: Алексей Торгашëв | K76: tilda | L76: cpc | M76: 708209804 | N76: 17657889986 | O76: Оклейка авто.tablet.Самара | Z76: 113747
A77: Daeewoo в цветную пленку / дорого | C77: Качественный лид | E77: Юрий | H77: 46207.841 | I77: Алексей Торгашëв | K77: tilda | L77: cpc | M77: 708209804 | N77: 17657889986 | O77: Обтяжка автомобиля пленкой.mobile.Стройкерамика | Z77: 113746
A78: Узнал стоимость пленки капот и крылья | B78: Звонок | C78: Качественный лид | H78: 46207.571 | I78: Виктор Худяков | Z78: 113735
A79: Оклейка мото 6,07 | B79: Звонок | C79: Качественный лид | H79: 46207.487 | I79: Алексей Торгашëв | Z79: 113730
A80: Оклейка ЗЛ двери Амарок | B80: Звонок | C80: Качественный лид | H80: 46206.568 | I80: Виктор Худяков | Z80: 113709
A81: плёнка антихром | B81: Звонок | C81: Качественный лид | H81: 46205.783 | I81: Александр Шушкин | Z81: 113684
A82: плёнка | B82: Звонок | C82: Качественный лид | H82: 46205.765 | I82: Александр Шушкин | Z82: 113683
A83: полная оклейка тенет | B83: Звонок | C83: Качественный лид | H83: 46205.74 | I83: Богдан Клименко | K83: google | L83: organic | M83: (none) | N83: (none) | O83: (none) | P83: mtoO4XVQ1NehfnBOaB57 | R83: 1.7829994e+18 | S83: Москва | T83: google | U83: organic | V83: (none) | W83: (none) | X83: (none) | Y83: 315 | Z83: 113681
A84: Лид #113680 | C84: Качественный лид | E84: Андрей | H84: 46205.719 | I84: Богдан Клименко | K84: tilda | L84: cpc | M84: 708209804 | N84: 17657889986 | O84: Оклейка машины.mobile.Красный Яр | Z84: 113680
A85: 7 937 652-81-18 - Входящий звонок | B85: Звонок | C85: Качественный лид | H85: 46205.619 | I85: Александр Шушкин | Z85: 113676
A86: тксист | B86: Звонок | C86: Качественный лид | H86: 46204.662 | I86: Александр Шушкин | K86: yandex | L86: cpc | M86: 708209804 | N86: 17657889986 | O86: Оклейка авто.mobile.Самара | P86: EGWOVnfj4EzSM42JYTMh | R86: 1.7829067e+18 | S86: Москва | T86: yandex | U86: cpc | V86: 708209804 | W86: 17657889986 | X86: Оклейка авто.mobile.Самара | Y86: 5 | Z86: 113647
A87: пленка хавал дорого | C87: Качественный лид | E87: Дмитрий | H87: 46204.646 | I87: Лида Левша | K87: tilda | L87: cpc | M87: 708209804 | N87: 17710448884 | O87: ---autotargeting.desktop.Самара | Z87: 113646
A88: плёнка | B88: Звонок | C88: Качественный лид | H88: 46204.483 | I88: Александр Шушкин | Z88: 113633
A89: омода оклейка зон под ручками 2000р | B89: Звонок | C89: Качественный лид | H89: 46204.449 | I89: Богдан Клименко | Z89: 113625
A90: tenet бронекпомлекс | B90: Звонок | C90: Качественный лид | H90: 46204.424 | I90: Богдан Клименко | K90: google | L90: organic | M90: (none) | N90: (none) | O90: (none) | P90: MeEAQQe5liMvB27GwZIs | R90: 1.7611202e+17 | T90: google | U90: organic | V90: (none) | W90: (none) | X90: (none) | Y90: 2 | Z90: 113622
A91: Плёнка | C91: Качественный лид | E91: ЕКАТЕРИНА | H91: 46203.454 | I91: Александр Шушкин | K91: tilda | L91: cpc | M91: 708209804 | N91: 17710448884 | O91: ---autotargeting.desktop.Самара | Z91: 113601
A92: плёнка | C92: Качественный лид | E92: Антон | H92: 46203.449 | I92: Александр Шушкин | K92: tilda | L92: cpc | M92: 708209804 | N92: 17710448884 | O92: ---autotargeting.mobile.Городское поселение Новосемейкино | Z92: 113600
A93: плёнка атлас | B93: ВКонтакте - Открытая линия Левша | C93: Качественный лид | E93: Владислав | G93: Топорков | H93: 46203.411 | I93: Александр Шушкин | Z93: 113597
A94: Рав4 новый пленка стандарт и тонировка | B94: Звонок | C94: Качественный лид | H94: 46202.778 | I94: Виктор Худяков | K94: yandex | L94: cpc | M94: 708209804 | N94: 17710448884 | O94: ---autotargeting.mobile.Самара | P94: TcDuZLgTlRs0Z7P6GxP8 | R94: 1.7827439e+18 | S94: Самара | T94: yandex | U94: cpc | V94: 708209804 | W94: 17710448884 | X94: ---autotargeting.mobile.Самара | Y94: 4 | Z94: 113591
A95: БМВ х7 зоны риска 4,07 | B95: Звонок | C95: Качественный лид | H95: 46202.762 | I95: Алексей Торгашëв | Z95: 113587
A96: Лид #113583 написал в чат ТГ | C96: Клиент не выходит на связь | E96: кристина | H96: 46202.667 | I96: Виктор Худяков | K96: tilda | L96: cpc | M96: 708209804 | N96: 17710448884 | O96: Оклейка кузова.mobile.Самара | Z96: 113583
A97: Полная оклейка Н5 | C97: Качественный лид | E97: Игорь | H97: 46201.788 | I97: Виктор Худяков | K97: tilda | L97: cpc | M97: 708209804 | N97: 17657889986 | O97: Обтянуть авто пленкой.mobile.Самара | Z97: 113553
A98: Гена Фадеев - Пленка ВК | B98: ВКонтакте - Открытая линия Левша | C98: Качественный лид | E98: Гена | G98: Фадеев | H98: 46201.569 | I98: Виктор Худяков | Z98: 113548
A99: 25,06 Крузак 300 пленка и полировка | B99: Звонок | C99: Качественный лид | H99: 46201.44 | I99: Виктор Худяков | Z99: 113544
A100: Лид #113535 | C100: Качественный лид | E100: Конев Александр Васильевич | H100: 46200.643 | I100: Лида Левша | K100: tilda | L100: cpc | M100: 708209804 | N100: 17710448884 | O100: ---autotargeting.desktop.Самара | Z100: 113535
...

Sheet Исходник — Wordstat
A1: Начало недели | B1: Конец недели | C1: Период Wordstat | D1: Число запросов | E1: Доля от всех запросов, %
A2: 44557 | B2: 44563 | C2: 27 декабря 2021 – 2 января 2022 | D2: 23 | E2: 0.000101
A3: 44564 | B3: 44570 | C3: 3 января 2022 – 9 января 2022 | D3: 31 | E3: 0.000139
A4: 44571 | B4: 44577 | C4: 10 января 2022 – 16 января 2022 | D4: 17 | E4: 6.3e-05
A5: 44578 | B5: 44584 | C5: 17 января 2022 – 23 января 2022 | D5: 25 | E5: 8.8e-05
A6: 44585 | B6: 44591 | C6: 24 января 2022 – 30 января 2022 | D6: 34 | E6: 0.000121
A7: 44592 | B7: 44598 | C7: 31 января 2022 – 6 февраля 2022 | D7: 35 | E7: 0.000123
A8: 44599 | B8: 44605 | C8: 7 февраля 2022 – 13 февраля 2022 | D8: 60 | E8: 0.000202
A9: 44606 | B9: 44612 | C9: 14 февраля 2022 – 20 февраля 2022 | D9: 43 | E9: 0.000143
A10: 44613 | B10: 44619 | C10: 21 февраля 2022 – 27 февраля 2022 | D10: 27 | E10: 9.5e-05
A11: 44620 | B11: 44626 | C11: 28 февраля 2022 – 6 марта 2022 | D11: 32 | E11: 0.000109
A12: 44627 | B12: 44633 | C12: 7 марта 2022 – 13 марта 2022 | D12: 23 | E12: 8e-05
A13: 44634 | B13: 44640 | C13: 14 марта 2022 – 20 марта 2022 | D13: 31 | E13: 0.000102
... A237: 46202 | B237: 46208 | C237: 29 июня 2026 – 5 июля 2026 | D237: 52 | E237: 0.000237
A238: 46209 | B238: 46215 | C238: 6 июля 2026 – 12 июля 2026 | D238: 85
